core.cpython-312-x86_64-linux-gnu.so
rl_env_core-1.0.2.dist-info/METADATA
rl_env_core-1.0.2.dist-info/WHEEL
rl_env_core-1.0.2.dist-info/top_level.txt
rl_env_core-1.0.2.dist-info/RECORD
